configs/__init__.py
configs/asgi.py
configs/settings.py
configs/wsgi.py
wdg_file_storage/__init__.py
wdg_file_storage/apps.py
wdg_file_storage/base.py
wdg_file_storage/constants.py
wdg_file_storage/tests.py
wdg_file_storage/backends/__init__.py
wdg_file_storage/backends/s3.py
wdg_file_storage/backends/s3_v01.py
wdg_file_storage/backends/storages.py
wdg_file_storage/helpers/__init__.py
wdg_file_storage/helpers/s3_helpers.py
wdg_file_storage/migrations/__init__.py
wdg_file_storage/models/__init__.py
wdg_file_storage/models/s3_file_storage_model.py
wdg_file_storage/utils/__init__.py
wdg_file_storage/utils/file_manager_util.py
wdg_file_storage/utils/file_util.py
wdg_file_storage-0.2.0.dist-info/LICENSE
wdg_file_storage-0.2.0.dist-info/METADATA
wdg_file_storage-0.2.0.dist-info/WHEEL
wdg_file_storage-0.2.0.dist-info/top_level.txt
wdg_file_storage-0.2.0.dist-info/RECORD
